engression/__init__.py
engression/engression.py
engression/loss_func.py
engression/models.py
engression/utils.py
engression/data/__init__.py
engression/data/loader.py
engression/data/simulator.py
engression-0.1.14.dist-info/LICENSE
engression-0.1.14.dist-info/METADATA
engression-0.1.14.dist-info/WHEEL
engression-0.1.14.dist-info/top_level.txt
engression-0.1.14.dist-info/RECORD
