Metadata-Version: 2.1
Name: engression
Version: 0.1.14
Summary: Engression Modelling
Home-page: https://github.com/xwshen51/engression
Author: Xinwei Shen and Nicolai Meinshausen
Author-email: xinwei.shen@stat.math.ethz.ch
License: BSD 3-Clause License
License-File: LICENSE
Requires-Dist: torch
Requires-Dist: numpy
Requires-Dist: matplotlib
